pytorch_math/__init__.py
pytorch_math/average.py
pytorch_math/result_type.py
pytorch_math-0.1.1.dist-info/LICENSE
pytorch_math-0.1.1.dist-info/METADATA
pytorch_math-0.1.1.dist-info/WHEEL
pytorch_math-0.1.1.dist-info/top_level.txt
pytorch_math-0.1.1.dist-info/RECORD
