Metadata-Version: 2.1
Name: pytorch-math
Version: 0.1.1
Summary: Pytorch Math
Home-page: UNKNOWN
Author: Daniel Kaminski de Souza
Author-email: daniel@kryptonunite.com
License: UNKNOWN
Platform: UNKNOWN
Classifier: Programming Language :: Python :: 3
Classifier: License :: OSI Approved :: GNU General Public License v3 (GPLv3)
Classifier: Operating System :: OS Independent
Requires-Python: >=3.6
Requires-Dist: torch
Provides-Extra: dev
Requires-Dist: pylint ; extra == 'dev'
Requires-Dist: pep8 ; extra == 'dev'
Requires-Dist: autopep8 ; extra == 'dev'
Requires-Dist: bumpversion ; extra == 'dev'
Requires-Dist: twine ; extra == 'dev'
Provides-Extra: docs
Provides-Extra: test
Requires-Dist: pytest (>=4.6) ; extra == 'test'
Requires-Dist: pytest-cov ; extra == 'test'
